conscommon/__init__.py
conscommon/data.py
conscommon/data_model/__init__.py
conscommon/data_model/agilent.py
conscommon/data_model/mks.py
conscommon/spreadsheet/__init__.py
conscommon/spreadsheet/parser.py
conscommon-0.0.8.dist-info/METADATA
conscommon-0.0.8.dist-info/WHEEL
conscommon-0.0.8.dist-info/top_level.txt
conscommon-0.0.8.dist-info/RECORD
