Metadata-Version: 2.1
Name: conscommon
Version: 0.0.8
Summary: Commons for Sirius applications
Home-page: https://github.com/lnls-sirius/cons-common/
Author: Carneiro, Claudio F.
License: GNU GPLv3
Download-URL: https://github.com/lnls-sirius/cons-common
Platform: UNKNOWN
Classifier: Intended Audience :: Science/Research
Classifier: Programming Language :: Python :: 3
Classifier: Topic :: Scientific/Engineering
Classifier: Operating System :: OS Independent
Requires-Python: >=3.6
Requires-Dist: requests (>=2.22.0)
